{
  "project_info": {
    "project_number": "700408981157",
    "project_id": "testkot-d12cc",
    "storage_bucket": "testkot-d12cc.firebasestorage.app"
  },
  "client": [
    {
      "client_info": {
        "mobilesdk_app_id": "1:700408981157:android:a5fbc5764fe21b08dd4f4c",
        "android_client_info": {
          "package_name": "com.sexychat.me"
        }
      },
      "oauth_client": [],
      "api_key": [
        {
          "current_key": "AIzaSyDeIo2jog5SZp-0dhvdTLRGWbYZRVhpi9c"
        }
      ],
      "services": {
        "appinvite_service": {
          "other_platform_oauth_client": []
        }
      }
    }
  ],
  "configuration_version": "1"
}

